fai/__init__.py
fai/_version.py
fai/env.py
fai/files.py
fai/subprocess.py
fai-0.1.0.dist-info/LICENSE
fai-0.1.0.dist-info/METADATA
fai-0.1.0.dist-info/WHEEL
fai-0.1.0.dist-info/top_level.txt
fai-0.1.0.dist-info/RECORD
