Metadata-Version: 2.1
Name: fai
Version: 0.1.0
Summary: FAI script integration lib
Home-page: https://github.com/st31ny/pyfai
Author: Maximilian Stein
Author-email: m@steiny.biz
License: MIT
Platform: UNKNOWN
Classifier: Programming Language :: Python :: 3
Classifier: License :: OSI Approved :: MIT License
Classifier: Operating System :: OS Independent
Requires-Python: >=3.7
License-File: LICENSE
Provides-Extra: dev
Requires-Dist: yapf ; extra == 'dev'
Requires-Dist: pylint ; extra == 'dev'
Requires-Dist: pytest ; extra == 'dev'
Requires-Dist: pytest-mock ; extra == 'dev'
Provides-Extra: doc
Requires-Dist: sphinx ; extra == 'doc'
Requires-Dist: sphinx-paramlinks ; extra == 'doc'
Requires-Dist: sphinx-autodoc-typehints ; extra == 'doc'
Provides-Extra: rtd
Requires-Dist: toml ; extra == 'rtd'
Requires-Dist: setuptools-scm[toml] ; extra == 'rtd'
